adamsnrc/__init__.py
adamsnrc/builder.py
adamsnrc/cli.py
adamsnrc/client.py
adamsnrc/config.py
adamsnrc/examples.py
adamsnrc/helpers.py
adamsnrc/main.py
adamsnrc/test_main.py
adamsnrc/types.py
adamsnrc/utils.py
adamsnrc-2.0.13.dist-info/licenses/LICENSE
adamsnrc-2.0.13.dist-info/METADATA
adamsnrc-2.0.13.dist-info/WHEEL
adamsnrc-2.0.13.dist-info/entry_points.txt
adamsnrc-2.0.13.dist-info/top_level.txt
adamsnrc-2.0.13.dist-info/RECORD
