Metadata-Version: 2.4
Name: adamsnrc
Version: 2.0.13
Summary: A robust Python client for the Nuclear Regulatory Commission's ADAMS API
Home-page: https://github.com/yourusername/adamsnrc
Author: Max Oliver
Author-email: Max Oliver <max.oliver@cintrax.com.br>
Maintainer-email: Max Oliver <max.oliver@cintrax.com.br>
License: MIT
Project-URL: Homepage, https://github.com/maxoliverbr/adamsnrc
Project-URL: Documentation, https://adamsnrc.readthedocs.io/
Project-URL: Repository, https://github.com/maxoliverbr/adamsnrc
Project-URL: Bug Tracker, https://github.com/maxoliverbr/adamsnrc/issues
Keywords: adams,nrc,nuclear,regulatory,api,client,documents
Classifier: Development Status :: 4 - Beta
Classifier: Intended Audience :: Developers
Classifier: Intended Audience :: Science/Research
Classifier: License :: OSI Approved :: MIT License
Classifier: Operating System :: OS Independent
Classifier: Programming Language :: Python :: 3
Classifier: Programming Language :: Python :: 3.8
Classifier: Programming Language :: Python :: 3.9
Classifier: Programming Language :: Python :: 3.10
Classifier: Programming Language :: Python :: 3.11
Classifier: Programming Language :: Python :: 3.12
Classifier: Topic :: Internet :: WWW/HTTP :: Dynamic Content
Classifier: Topic :: Scientific/Engineering :: Information Analysis
Classifier: Topic :: Software Development :: Libraries :: Python Modules
Requires-Python: >=3.9
License-File: LICENSE
Requires-Dist: requests>=2.28.0
Requires-Dist: typing-extensions>=4.0.0
Provides-Extra: dev
Requires-Dist: pytest>=7.0.0; extra == "dev"
Requires-Dist: pytest-mock>=3.8.0; extra == "dev"
Requires-Dist: pytest-cov>=4.0.0; extra == "dev"
Requires-Dist: ruff>=0.1.0; extra == "dev"
Requires-Dist: mypy>=1.0.0; extra == "dev"
Requires-Dist: twine>=4.0.0; extra == "dev"
Requires-Dist: build>=0.10.0; extra == "dev"
Provides-Extra: docs
Requires-Dist: sphinx>=5.0.0; extra == "docs"
Requires-Dist: sphinx-rtd-theme>=1.0.0; extra == "docs"
Requires-Dist: myst-parser>=0.18.0; extra == "docs"
Dynamic: author
Dynamic: home-page
Dynamic: license-file
Dynamic: requires-python
